migrations/env.py
migrations/script.py.mako
migrations/versions/a04dfe729866_git_commit_79a9ba5.py
migrations/versions/ed27db582ea8_git_commit_1910ba8.py
publications/.gitignore
publications/icssi-code-authors.ipynb
publications/qss-code-authors/.gitignore
publications/qss-code-authors/_quarto.yml
publications/qss-code-authors/main.bib
publications/qss-code-authors/qss-code-authors.qmd
publications/qss-code-authors/_extensions/andrewheiss/wordcount/_extension.yml
publications/qss-code-authors/_extensions/andrewheiss/wordcount/banner.html
publications/qss-code-authors/_extensions/andrewheiss/wordcount/citeproc.lua
publications/qss-code-authors/_extensions/andrewheiss/wordcount/wordcount.lua
publications/qss-code-authors/_extensions/andrewheiss/wordcount/words.lua
publications/qss-code-authors/_extensions/mikemahoney218/arxiv/_extension.yml
publications/qss-code-authors/_extensions/mikemahoney218/arxiv/arxiv.sty
publications/qss-code-authors/_extensions/mikemahoney218/arxiv/orcidlink.sty
publications/qss-code-authors/_extensions/mikemahoney218/arxiv/shortcodes.lua
publications/qss-code-authors/_extensions/mikemahoney218/arxiv/partials/_authors.tex
publications/qss-code-authors/_extensions/mikemahoney218/arxiv/partials/before-body.tex
publications/qss-code-authors/_extensions/mikemahoney218/arxiv/partials/title.tex
publications/qss-code-authors/_extensions/quarto-journals/elsevier/_extension.yml
publications/qss-code-authors/_extensions/quarto-journals/elsevier/elsarticle.cls
publications/qss-code-authors/_extensions/quarto-journals/elsevier/elsevier.lua
publications/qss-code-authors/_extensions/quarto-journals/elsevier/bib/elsarticle-harv.bst
publications/qss-code-authors/_extensions/quarto-journals/elsevier/bib/elsarticle-num-names.bst
publications/qss-code-authors/_extensions/quarto-journals/elsevier/bib/elsarticle-num.bst
publications/qss-code-authors/_extensions/quarto-journals/elsevier/bib/elsevier-harvard.csl
rs_graph-0.1.0.dist-info/licenses/LICENSE
rs_graph-0.1.0.dist-info/METADATA
rs_graph-0.1.0.dist-info/WHEEL
rs_graph-0.1.0.dist-info/entry_points.txt
rs_graph-0.1.0.dist-info/top_level.txt
rs_graph-0.1.0.dist-info/RECORD
