Metadata-Version: 2.4
Name: rs-graph
Version: 0.1.0
Summary: Exploring research software
Author-email: Eva Maxfield Brown <evamaxfieldbrown@gmail.com>
License: MIT License
Project-URL: Homepage, https://github.com/evamaxfield/rs-graph
Project-URL: Bug Tracker, https://github.com/evamaxfield/rs-graph/issues
Project-URL: Documentation, https://evamaxfield.github.io/rs-graph
Project-URL: User Support, https://github.com/evamaxfield/rs-graph/issues
Classifier: Development Status :: 4 - Beta
Classifier: Natural Language :: English
Classifier: Programming Language :: Python :: 3.11
Classifier: Programming Language :: Python :: 3.12
Classifier: Programming Language :: Python :: 3.13
Requires-Python: >=3.11
License-File: LICENSE
Requires-Dist: sqlmodel<0.0.17,>=0.0.16
Provides-Extra: lint
Requires-Dist: pre-commit>=2.20.0; extra == "lint"
Provides-Extra: dev
Requires-Dist: ipython; extra == "dev"
Requires-Dist: jupyterlab; extra == "dev"
Requires-Dist: alembic[tz]<2,>=1; extra == "dev"
Provides-Extra: modeling
Requires-Dist: ipython; extra == "modeling"
Requires-Dist: lxml<6,>=5; extra == "modeling"
Requires-Dist: matplotlib==3.8.4; extra == "modeling"
Requires-Dist: numpy<3,>=1; extra == "modeling"
Requires-Dist: opinionated<0.0.4,>=0.0.3; extra == "modeling"
Requires-Dist: pandas<3,>=1; extra == "modeling"
Requires-Dist: pyarrow>=12; extra == "modeling"
Requires-Dist: scipy<2,>=1; extra == "modeling"
Requires-Dist: sci-soft-models>=0.2; extra == "modeling"
Requires-Dist: seaborn<0.14,>=0.13; extra == "modeling"
Requires-Dist: statsmodels<0.15,>=0.14; extra == "modeling"
Provides-Extra: data
Requires-Dist: dataclasses-json<0.7,>=0.6; extra == "data"
Requires-Dist: dvuploader>=0.3; extra == "data"
Requires-Dist: easyDataverse<0.5,>=0.4; extra == "data"
Requires-Dist: python-dotenv<2,>=1; extra == "data"
Requires-Dist: tqdm<5,>=4; extra == "data"
Requires-Dist: typer>=0.12; extra == "data"
Provides-Extra: pipeline
Requires-Dist: allofplos<2,>=1; extra == "pipeline"
Requires-Dist: backoff<3,>=2; extra == "pipeline"
Requires-Dist: bokeh<4,>=3; extra == "pipeline"
Requires-Dist: coiled<2,>=1; extra == "pipeline"
Requires-Dist: dataclasses-json<0.7,>=0.6; extra == "pipeline"
Requires-Dist: gcsfs>=2023.10.0; extra == "pipeline"
Requires-Dist: ghapi<2,>=1; extra == "pipeline"
Requires-Dist: gh-tokens-loader<0.2,>=0.1; extra == "pipeline"
Requires-Dist: msgspec<0.19,>=0.18; extra == "pipeline"
Requires-Dist: numpy<3,>=1; extra == "pipeline"
Requires-Dist: parse<2,>=1; extra == "pipeline"
Requires-Dist: pandas<3,>=1; extra == "pipeline"
Requires-Dist: prefect<4,>=3; extra == "pipeline"
Requires-Dist: pyalex<0.15,>=0.14; extra == "pipeline"
Requires-Dist: pyarrow>=12; extra == "pipeline"
Requires-Dist: pybliometrics<5,>=4.3; extra == "pipeline"
Requires-Dist: python-dotenv<2,>=1; extra == "pipeline"
Requires-Dist: pyyaml<7,>=6; extra == "pipeline"
Requires-Dist: requests<3,>=2; extra == "pipeline"
Requires-Dist: sci-soft-models>=0.2; extra == "pipeline"
Requires-Dist: tqdm<5,>=4; extra == "pipeline"
Requires-Dist: typer>=0.12; extra == "pipeline"
Dynamic: license-file
